ulf2english/__init__.py
ulf2english/file.py
ulf2english/patternlib.py
ulf2english/sexpr.py
ulf2english/ulf2english.py
ulf2english/util.py
ulf2english/resources/wordnet.adv
ulf2english-0.1.1.dist-info/METADATA
ulf2english-0.1.1.dist-info/WHEEL
ulf2english-0.1.1.dist-info/licenses/LICENSE
ulf2english-0.1.1.dist-info/RECORD
