Metadata-Version: 2.1
Name: ulf2english
Version: 0.1.1
Summary: A Python port of the Lisp ulf2english package by Gene Kim.
Project-URL: Homepage, https://github.com/bkane2/ulf2english-py
Project-URL: Bug Tracker, https://github.com/bkane2/ulf2english-py/issues
Author-email: Benjamin Kane <Ben.Kane@me.com>, Gene Kim <genekim@usf.edu>
License-File: LICENSE
Classifier: License :: OSI Approved :: MIT License
Classifier: Operating System :: OS Independent
Classifier: Programming Language :: Python :: 3
Requires-Python: >=3.7
Requires-Dist: memoization>=0.4.0
Requires-Dist: pattern>=3.6
Requires-Dist: transduction>=0.1.3
Requires-Dist: ulflib>=0.0.11
